flashcard_generator/__init__.py
flashcard_generator/generator.py
flashcard_generator-0.1.1.dist-info/LICENSE
flashcard_generator-0.1.1.dist-info/METADATA
flashcard_generator-0.1.1.dist-info/WHEEL
flashcard_generator-0.1.1.dist-info/RECORD
