Metadata-Version: 2.1
Name: flashcard-generator
Version: 0.1.1
Summary: 
License: MIT
Author: Steven Van Ingelgem
Author-email: steven@vaningelgem.be
Requires-Python: >=3.8,<4.0
Classifier: License :: OSI Approved :: MIT License
Classifier: Programming Language :: Python :: 3
Classifier: Programming Language :: Python :: 3.8
Classifier: Programming Language :: Python :: 3.9
Classifier: Programming Language :: Python :: 3.10
Classifier: Programming Language :: Python :: 3.11
Classifier: Programming Language :: Python :: 3.12
Requires-Dist: reportlab (>=4.2.2,<5.0.0)
